INSTALL
LICENSE
README.rst
setup.cfg
setup.py
xmlprops/__init__.py
xmlprops/example.py
xmlprops/expandvars.py
xmlprops/props.py
xmlprops.egg-info/PKG-INFO
xmlprops.egg-info/SOURCES.txt
xmlprops.egg-info/dependency_links.txt
xmlprops.egg-info/requires.txt
xmlprops.egg-info/top_level.txt