Metadata-Version: 1.1
Name: xmlprops
Version: 2.0.0
Summary: XMLProps allows the use XML based properties files similar to Java.
Home-page: https://github.com/Acrisel/xmlprops
Author: Acrisel Team
Author-email: support@acrisel.com
License: MIT
Keywords: project,virtualenv,parameters
Platform: UNKNOWN
Classifier: Development Status :: 5 - Production/Stable
Classifier: Environment :: Other Environment
Classifier: Framework :: Project Settings and Operation
Classifier: Intended Audience :: Developers
Classifier: License :: OSI Approved :: MIT License
Classifier: Operating System :: OS Independent
Classifier: Programming Language :: Python
Classifier: Programming Language :: Python :: 3
Classifier: Programming Language :: Python :: 3.2
Classifier: Programming Language :: Python :: 3.3
Classifier: Programming Language :: Python :: 3.4
Classifier: Programming Language :: Python :: 3.5
Classifier: Topic :: Software Development :: Libraries :: Application Frameworks
Classifier: Topic :: Software Development :: Libraries :: Python Modules
